maze_library/__init__.py
maze_library/maze_library.py
egoloven_maze_lib-0.1.0.dist-info/LICENSE
egoloven_maze_lib-0.1.0.dist-info/LICENSE.txt
egoloven_maze_lib-0.1.0.dist-info/METADATA
egoloven_maze_lib-0.1.0.dist-info/WHEEL
egoloven_maze_lib-0.1.0.dist-info/top_level.txt
egoloven_maze_lib-0.1.0.dist-info/RECORD
